stanfordpy/graphics/__init__.py
stanfordpy/graphics/click_tracker.py
stanfordpy/graphics/colors.py
stanfordpy/graphics/graphics.py
stanfordpy/graphics/keyboard_tracker.py
stanfordpy/graphics/utils.py
stanfordpy_graphics-0.0.5.dist-info/METADATA
stanfordpy_graphics-0.0.5.dist-info/WHEEL
stanfordpy_graphics-0.0.5.dist-info/top_level.txt
stanfordpy_graphics-0.0.5.dist-info/RECORD
